setup.py
gmail3/__init__.py
gmail3/exceptions.py
gmail3/gmail.py
gmail3/mailbox.py
gmail3/message.py
gmail3/utf.py
gmail3/utils.py
gmail3.egg-info/PKG-INFO
gmail3.egg-info/SOURCES.txt
gmail3.egg-info/dependency_links.txt
gmail3.egg-info/top_level.txt