Metadata-Version: 1.1
Name: gmail3
Version: 0.0.6
Summary: A Pythonic (for Python3.x) interface for Google Mail.
Home-page: https://github.com/kriskavalieri/gmail
Author: Kris Kavalieri
Author-email: UNKNOWN
License: MIT
Download-URL: https://github.com/kriskavalieri/gmail/tarball/master
Keywords: google gmail3
Platform: UNKNOWN
Classifier: Development Status :: 3 - Alpha
Classifier: Topic :: Communications :: Email
Classifier: License :: OSI Approved :: MIT License
